method_versioning/__init__.py
method_versioning/decorator.py
method_versioning-0.0.2.dist-info/LICENSE
method_versioning-0.0.2.dist-info/METADATA
method_versioning-0.0.2.dist-info/WHEEL
method_versioning-0.0.2.dist-info/top_level.txt
method_versioning-0.0.2.dist-info/RECORD
