Metadata-Version: 2.1
Name: method-versioning
Version: 0.0.2
Summary: Method versioning package
Home-page: https://github.com/nrhys2005/method-versioning
Author: Sanghun Lee
Author-email: nrhys2005@gmail.com
License: UNKNOWN
Platform: UNKNOWN
Classifier: Programming Language :: Python :: 3
Classifier: License :: OSI Approved :: MIT License
Classifier: Operating System :: OS Independent
Classifier: Development Status :: 4 - Beta
Classifier: Intended Audience :: Developers
Classifier: Topic :: Software Development :: Libraries
Requires-Python: >=3.6
License-File: LICENSE
